open_retrieval/__init__.py
open_retrieval/document_loaders.py
open_retrieval/embedding_providers.py
open_retrieval/retrievers.py
open_retrieval/text_splitters.py
open_retrieval/vector_databases.py
open_retrieval/utils/classifier.py
open_retrieval/utils/config.py
open_retrieval/utils/llms.py
open_retrieval/utils/rephrasor.py
open_retrieval-0.0.2.dist-info/LICENSE
open_retrieval-0.0.2.dist-info/METADATA
open_retrieval-0.0.2.dist-info/WHEEL
open_retrieval-0.0.2.dist-info/top_level.txt
open_retrieval-0.0.2.dist-info/RECORD
