Metadata-Version: 2.1
Name: open_retrieval
Version: 0.0.2
Summary: A retrieval package build on top of Open source models
Author-email: Koleshjr <koleshjr@gmail.com>
License: Apache License
Project-URL: Homepage, https://github.com/koleshjr/open_retrieval
Keywords: document loaders,embedding providers,text splitters,vector databases,retrivers
Classifier: License :: OSI Approved :: Apache Software License
Classifier: Programming Language :: Python :: 3
Requires-Python: >=3.9
License-File: LICENSE
Requires-Dist: langchain-community >=0.2.1
Requires-Dist: qdrant-client >=1.9.1
Requires-Dist: rerankers[transformers] >=0.3.0
Requires-Dist: sentence-transformers >=2.7.0
Requires-Dist: unstructured >=0.14.2
Requires-Dist: python-docx >=1.1.2
Requires-Dist: chromadb >=0.5.0
Requires-Dist: langchain >=0.2.1
Requires-Dist: Markdown >=3.6
Requires-Dist: beautifulsoup4 >=4.12.3
Requires-Dist: langchain-experimental >=0.0.59
Requires-Dist: nltk >=3.8.1
Requires-Dist: fastembed >=0.2.7
Requires-Dist: pymilvus >=2.4.1
Requires-Dist: docarray >=0.40.0
Requires-Dist: faiss-cpu >=1.8.0
Requires-Dist: unstructured[pdf] >=0.14.2
Provides-Extra: dev
Requires-Dist: black ; extra == 'dev'
Requires-Dist: bumpver ; extra == 'dev'
Requires-Dist: isort ; extra == 'dev'
Requires-Dist: pip-tools ; extra == 'dev'
Requires-Dist: pytest ; extra == 'dev'
